agentdev/__init__.py
agentdev/__main__.py
agentdev/_bootstrap.py
agentdev/_hooks.py
agentdev/cli.py
agentdev/localdebug.py
agentdev/backend/__init__.py
agentdev/backend/_conversations.py
agentdev/backend/_utils.py
agentdev/backend/code_analyzer.py
agentdev/backend/errors.py
agentdev/backend/event_mapper.py
agentdev/backend/server.py
agentdev/backend/structs/__init__.py
agentdev/backend/structs/entity_response.py
agentdev/backend/structs/request.py
agent_dev_cli-0.0.1b251223.dist-info/entry_points.txt
agent_dev_cli-0.0.1b251223.dist-info/WHEEL
agent_dev_cli-0.0.1b251223.dist-info/METADATA
agent_dev_cli-0.0.1b251223.dist-info/RECORD
