Metadata-Version: 2.4
Name: agent-dev-cli
Version: 0.0.1b251223
Summary: AI Toolkit - CLI and SDK for agent debugging and workflow visualization
Keywords: ai,agent,toolkit,debugging,workflow,visualization
Requires-Python: >=3.10.0
Classifier: Development Status :: 4 - Beta
Classifier: Intended Audience :: Developers
Classifier: Operating System :: OS Independent
Classifier: Programming Language :: Python :: 3
Classifier: Programming Language :: Python :: 3.10
Classifier: Programming Language :: Python :: 3.11
Classifier: Programming Language :: Python :: 3.12
Classifier: Programming Language :: Python :: 3.13
Classifier: Topic :: Software Development :: Debuggers
Classifier: Topic :: Software Development :: Libraries :: Python Modules
Classifier: Typing :: Typed
Requires-Dist: pydantic>=2.12.4
Requires-Dist: azure-identity>=1.25.1
Requires-Dist: python-dotenv>=1.2.1
Requires-Dist: azure-ai-agents>=1.2.0b5
Requires-Dist: starlette>=0.49.3
Requires-Dist: openai>=1.109.1
Requires-Dist: agent-framework-azure-ai>=1.0.0b251211
Requires-Dist: azure-ai-agentserver-agentframework>=1.0.0b7
Requires-Dist: azure-ai-agentserver-core>=1.0.0b7
Requires-Dist: click>=8.1.0
Requires-Dist: azure-ai-projects>=2.0.0b2
Requires-Dist: pytest>=8.0.0 ; extra == "dev"
Requires-Dist: pytest-asyncio>=0.23.0 ; extra == "dev"
Requires-Dist: pytest-cov>=4.1.0 ; extra == "dev"
Requires-Dist: httpx>=0.27.0 ; extra == "dev"
Project-URL: Documentation, https://github.com/microsoft/vscode-ai-toolkit#readme
Project-URL: Homepage, https://github.com/microsoft/vscode-ai-toolkit
Project-URL: Issues, https://github.com/microsoft/vscode-ai-toolkit/issues
Project-URL: Repository, https://github.com/microsoft/vscode-ai-toolkit
Provides-Extra: dev
